Workbook

Sheet Summary
A1: ERM Gap Analysis Scorecard
A2: Current solution benchmarked against Corporater ERM and the world-class ERM/GRC field
A3: Prepared 8 August 2026 | Companion to 00_ERM_REMODEL_MASTER_PLAN.md and 01_EXECUTION_PROMPT_PACK.md
A5: Coverage by domain
A7: Domain | B7: Items | C7: Strong | D7: Present | E7: Partial | F7: Mock | G7: Absent | H7: Covered (Strong+Present) | I7: Coverage % | J7: Weighted coverage % | K7: P0 | L7: P1
A8: A. Platform architecture & data model | B8: =COUNTIF(Scorecard!$B$2:$B$351,$A8) -> 25 | C8: =COUNTIFS(Scorecard!$B$2:$B$351,$A8,Scorecard!$F$2:$F$351,"Strong") -> 0 | D8: =COUNTIFS(Scorecard!$B$2:$B$351,$A8,Scorecard!$F$2:$F$351,"Present") -> 0 | E8: =COUNTIFS(Scorecard!$B$2:$B$351,$A8,Scorecard!$F$2:$F$351,"Partial") -> 7 | F8: =COUNTIFS(Scorecard!$B$2:$B$351,$A8,Scorecard!$F$2:$F$351,"Mock") -> 0 | G8: =COUNTIFS(Scorecard!$B$2:$B$351,$A8,Scorecard!$F$2:$F$351,"Absent") -> 18 | H8: =C8+D8 -> 0 | I8: =IFERROR(H8/B8,0) -> 0 | J8: =IFERROR((C8*1+D8*0.85+E8*0.4+F8*0.05)/B8,0) -> 0.112 | K8: =COUNTIFS(Scorecard!$B$2:$B$351,$A8,Scorecard!$G$2:$G$351,"P0") -> 2 | L8: =COUNTIFS(Scorecard!$B$2:$B$351,$A8,Scorecard!$G$2:$G$351,"P1") -> 13
A9: B. Risk taxonomy, register & appetite | B9: =COUNTIF(Scorecard!$B$2:$B$351,$A9) -> 22 | C9: =COUNTIFS(Scorecard!$B$2:$B$351,$A9,Scorecard!$F$2:$F$351,"Strong") -> 1 | D9: =COUNTIFS(Scorecard!$B$2:$B$351,$A9,Scorecard!$F$2:$F$351,"Present") -> 4 | E9: =COUNTIFS(Scorecard!$B$2:$B$351,$A9,Scorecard!$F$2:$F$351,"Partial") -> 7 | F9: =COUNTIFS(Scorecard!$B$2:$B$351,$A9,Scorecard!$F$2:$F$351,"Mock") -> 1 | G9: =COUNTIFS(Scorecard!$B$2:$B$351,$A9,Scorecard!$F$2:$F$351,"Absent") -> 9 | H9: =C9+D9 -> 5 | I9: =IFERROR(H9/B9,0) -> 0.22727273 | J9: =IFERROR((C9*1+D9*0.85+E9*0.4+F9*0.05)/B9,0) -> 0.32954545 | K9: =COUNTIFS(Scorecard!$B$2:$B$351,$A9,Scorecard!$G$2:$G$351,"P0") -> 0 | L9: =COUNTIFS(Scorecard!$B$2:$B$351,$A9,Scorecard!$G$2:$G$351,"P1") -> 14
A10: C. Assessment, analysis & methodology | B10: =COUNTIF(Scorecard!$B$2:$B$351,$A10) -> 23 | C10: =COUNTIFS(Scorecard!$B$2:$B$351,$A10,Scorecard!$F$2:$F$351,"Strong") -> 2 | D10: =COUNTIFS(Scorecard!$B$2:$B$351,$A10,Scorecard!$F$2:$F$351,"Present") -> 2 | E10: =COUNTIFS(Scorecard!$B$2:$B$351,$A10,Scorecard!$F$2:$F$351,"Partial") -> 5 | F10: =COUNTIFS(Scorecard!$B$2:$B$351,$A10,Scorecard!$F$2:$F$351,"Mock") -> 0 | G10: =COUNTIFS(Scorecard!$B$2:$B$351,$A10,Scorecard!$F$2:$F$351,"Absent") -> 14 | H10: =C10+D10 -> 4 | I10: =IFERROR(H10/B10,0) -> 0.17391304 | J10: =IFERROR((C10*1+D10*0.85+E10*0.4+F10*0.05)/B10,0) -> 0.24782609 | K10: =COUNTIFS(Scorecard!$B$2:$B$351,$A10,Scorecard!$G$2:$G$351,"P0") -> 1 | L10: =COUNTIFS(Scorecard!$B$2:$B$351,$A10,Scorecard!$G$2:$G$351,"P1") -> 6
A11: D. Risk quantification | B11: =COUNTIF(Scorecard!$B$2:$B$351,$A11) -> 18 | C11: =COUNTIFS(Scorecard!$B$2:$B$351,$A11,Scorecard!$F$2:$F$351,"Strong") -> 1 | D11: =COUNTIFS(Scorecard!$B$2:$B$351,$A11,Scorecard!$F$2:$F$351,"Present") -> 1 | E11: =COUNTIFS(Scorecard!$B$2:$B$351,$A11,Scorecard!$F$2:$F$351,"Partial") -> 6 | F11: =COUNTIFS(Scorecard!$B$2:$B$351,$A11,Scorecard!$F$2:$F$351,"Mock") -> 0 | G11: =COUNTIFS(Scorecard!$B$2:$B$351,$A11,Scorecard!$F$2:$F$351,"Absent") -> 10 | H11: =C11+D11 -> 2 | I11: =IFERROR(H11/B11,0) -> 0.11111111 | J11: =IFERROR((C11*1+D11*0.85+E11*0.4+F11*0.05)/B11,0) -> 0.23611111 | K11: =COUNTIFS(Scorecard!$B$2:$B$351,$A11,Scorecard!$G$2:$G$351,"P0") -> 0 | L11: =COUNTIFS(Scorecard!$B$2:$B$351,$A11,Scorecard!$G$2:$G$351,"P1") -> 2
A12: E. Controls & control monitoring | B12: =COUNTIF(Scorecard!$B$2:$B$351,$A12) -> 20 | C12: =COUNTIFS(Scorecard!$B$2:$B$351,$A12,Scorecard!$F$2:$F$351,"Strong") -> 2 | D12: =COUNTIFS(Scorecard!$B$2:$B$351,$A12,Scorecard!$F$2:$F$351,"Present") -> 2 | E12: =COUNTIFS(Scorecard!$B$2:$B$351,$A12,Scorecard!$F$2:$F$351,"Partial") -> 2 | F12: =COUNTIFS(Scorecard!$B$2:$B$351,$A12,Scorecard!$F$2:$F$351,"Mock") -> 0 | G12: =COUNTIFS(Scorecard!$B$2:$B$351,$A12,Scorecard!$F$2:$F$351,"Absent") -> 14 | H12: =C12+D12 -> 4 | I12: =IFERROR(H12/B12,0) -> 0.2 | J12: =IFERROR((C12*1+D12*0.85+E12*0.4+F12*0.05)/B12,0) -> 0.225 | K12: =COUNTIFS(Scorecard!$B$2:$B$351,$A12,Scorecard!$G$2:$G$351,"P0") -> 0 | L12: =COUNTIFS(Scorecard!$B$2:$B$351,$A12,Scorecard!$G$2:$G$351,"P1") -> 3
A13: F. Compliance, obligations & regulatory change | B13: =COUNTIF(Scorecard!$B$2:$B$351,$A13) -> 18 | C13: =COUNTIFS(Scorecard!$B$2:$B$351,$A13,Scorecard!$F$2:$F$351,"Strong") -> 0 | D13: =COUNTIFS(Scorecard!$B$2:$B$351,$A13,Scorecard!$F$2:$F$351,"Present") -> 1 | E13: =COUNTIFS(Scorecard!$B$2:$B$351,$A13,Scorecard!$F$2:$F$351,"Partial") -> 3 | F13: =COUNTIFS(Scorecard!$B$2:$B$351,$A13,Scorecard!$F$2:$F$351,"Mock") -> 1 | G13: =COUNTIFS(Scorecard!$B$2:$B$351,$A13,Scorecard!$F$2:$F$351,"Absent") -> 13 | H13: =C13+D13 -> 1 | I13: =IFERROR(H13/B13,0) -> 0.055555556 | J13: =IFERROR((C13*1+D13*0.85+E13*0.4+F13*0.05)/B13,0) -> 0.11666667 | K13: =COUNTIFS(Scorecard!$B$2:$B$351,$A13,Scorecard!$G$2:$G$351,"P0") -> 0 | L13: =COUNTIFS(Scorecard!$B$2:$B$351,$A13,Scorecard!$G$2:$G$351,"P1") -> 5
A14: G. Policy management | B14: =COUNTIF(Scorecard!$B$2:$B$351,$A14) -> 10 | C14: =COUNTIFS(Scorecard!$B$2:$B$351,$A14,Scorecard!$F$2:$F$351,"Strong") -> 0 | D14: =COUNTIFS(Scorecard!$B$2:$B$351,$A14,Scorecard!$F$2:$F$351,"Present") -> 0 | E14: =COUNTIFS(Scorecard!$B$2:$B$351,$A14,Scorecard!$F$2:$F$351,"Partial") -> 0 | F14: =COUNTIFS(Scorecard!$B$2:$B$351,$A14,Scorecard!$F$2:$F$351,"Mock") -> 0 | G14: =COUNTIFS(Scorecard!$B$2:$B$351,$A14,Scorecard!$F$2:$F$351,"Absent") -> 10 | H14: =C14+D14 -> 0 | I14: =IFERROR(H14/B14,0) -> 0 | J14: =IFERROR((C14*1+D14*0.85+E14*0.4+F14*0.05)/B14,0) -> 0 | K14: =COUNTIFS(Scorecard!$B$2:$B$351,$A14,Scorecard!$G$2:$G$351,"P0") -> 0 | L14: =COUNTIFS(Scorecard!$B$2:$B$351,$A14,Scorecard!$G$2:$G$351,"P1") -> 0
A15: H. Internal audit & assurance | B15: =COUNTIF(Scorecard!$B$2:$B$351,$A15) -> 18 | C15: =COUNTIFS(Scorecard!$B$2:$B$351,$A15,Scorecard!$F$2:$F$351,"Strong") -> 0 | D15: =COUNTIFS(Scorecard!$B$2:$B$351,$A15,Scorecard!$F$2:$F$351,"Present") -> 1 | E15: =COUNTIFS(Scorecard!$B$2:$B$351,$A15,Scorecard!$F$2:$F$351,"Partial") -> 2 | F15: =COUNTIFS(Scorecard!$B$2:$B$351,$A15,Scorecard!$F$2:$F$351,"Mock") -> 0 | G15: =COUNTIFS(Scorecard!$B$2:$B$351,$A15,Scorecard!$F$2:$F$351,"Absent") -> 15 | H15: =C15+D15 -> 1 | I15: =IFERROR(H15/B15,0) -> 0.055555556 | J15: =IFERROR((C15*1+D15*0.85+E15*0.4+F15*0.05)/B15,0) -> 0.091666667 | K15: =COUNTIFS(Scorecard!$B$2:$B$351,$A15,Scorecard!$G$2:$G$351,"P0") -> 0 | L15: =COUNTIFS(Scorecard!$B$2:$B$351,$A15,Scorecard!$G$2:$G$351,"P1") -> 0
A16: I. Incidents, events, issues & actions | B16: =COUNTIF(Scorecard!$B$2:$B$351,$A16) -> 16 | C16: =COUNTIFS(Scorecard!$B$2:$B$351,$A16,Scorecard!$F$2:$F$351,"Strong") -> 5 | D16: =COUNTIFS(Scorecard!$B$2:$B$351,$A16,Scorecard!$F$2:$F$351,"Present") -> 6 | E16: =COUNTIFS(Scorecard!$B$2:$B$351,$A16,Scorecard!$F$2:$F$351,"Partial") -> 1 | F16: =COUNTIFS(Scorecard!$B$2:$B$351,$A16,Scorecard!$F$2:$F$351,"Mock") -> 1 | G16: =COUNTIFS(Scorecard!$B$2:$B$351,$A16,Scorecard!$F$2:$F$351,"Absent") -> 3 | H16: =C16+D16 -> 11 | I16: =IFERROR(H16/B16,0) -> 0.6875 | J16: =IFERROR((C16*1+D16*0.85+E16*0.4+F16*0.05)/B16,0) -> 0.659375 | K16: =COUNTIFS(Scorecard!$B$2:$B$351,$A16,Scorecard!$G$2:$G$351,"P0") -> 0 | L16: =COUNTIFS(Scorecard!$B$2:$B$351,$A16,Scorecard!$G$2:$G$351,"P1") -> 1
A17: J. Third-party & supply chain risk | B17: =COUNTIF(Scorecard!$B$2:$B$351,$A17) -> 19 | C17: =COUNTIFS(Scorecard!$B$2:$B$351,$A17,Scorecard!$F$2:$F$351,"Strong") -> 0 | D17: =COUNTIFS(Scorecard!$B$2:$B$351,$A17,Scorecard!$F$2:$F$351,"Present") -> 0 | E17: =COUNTIFS(Scorecard!$B$2:$B$351,$A17,Scorecard!$F$2:$F$351,"Partial") -> 0 | F17: =COUNTIFS(Scorecard!$B$2:$B$351,$A17,Scorecard!$F$2:$F$351,"Mock") -> 0 | G17: =COUNTIFS(Scorecard!$B$2:$B$351,$A17,Scorecard!$F$2:$F$351,"Absent") -> 19 | H17: =C17+D17 -> 0 | I17: =IFERROR(H17/B17,0) -> 0 | J17: =IFERROR((C17*1+D17*0.85+E17*0.4+F17*0.05)/B17,0) -> 0 | K17: =COUNTIFS(Scorecard!$B$2:$B$351,$A17,Scorecard!$G$2:$G$351,"P0") -> 0 | L17: =COUNTIFS(Scorecard!$B$2:$B$351,$A17,Scorecard!$G$2:$G$351,"P1") -> 0
A18: K. Operational resilience & BCM | B18: =COUNTIF(Scorecard!$B$2:$B$351,$A18) -> 17 | C18: =COUNTIFS(Scorecard!$B$2:$B$351,$A18,Scorecard!$F$2:$F$351,"Strong") -> 0 | D18: =COUNTIFS(Scorecard!$B$2:$B$351,$A18,Scorecard!$F$2:$F$351,"Present") -> 0 | E18: =COUNTIFS(Scorecard!$B$2:$B$351,$A18,Scorecard!$F$2:$F$351,"Partial") -> 0 | F18: =COUNTIFS(Scorecard!$B$2:$B$351,$A18,Scorecard!$F$2:$F$351,"Mock") -> 0 | G18: =COUNTIFS(Scorecard!$B$2:$B$351,$A18,Scorecard!$F$2:$F$351,"Absent") -> 17 | H18: =C18+D18 -> 0 | I18: =IFERROR(H18/B18,0) -> 0 | J18: =IFERROR((C18*1+D18*0.85+E18*0.4+F18*0.05)/B18,0) -> 0 | K18: =COUNTIFS(Scorecard!$B$2:$B$351,$A18,Scorecard!$G$2:$G$351,"P0") -> 0 | L18: =COUNTIFS(Scorecard!$B$2:$B$351,$A18,Scorecard!$G$2:$G$351,"P1") -> 0
A19: L. ESG & sustainability | B19: =COUNTIF(Scorecard!$B$2:$B$351,$A19) -> 12 | C19: =COUNTIFS(Scorecard!$B$2:$B$351,$A19,Scorecard!$F$2:$F$351,"Strong") -> 0 | D19: =COUNTIFS(Scorecard!$B$2:$B$351,$A19,Scorecard!$F$2:$F$351,"Present") -> 0 | E19: =COUNTIFS(Scorecard!$B$2:$B$351,$A19,Scorecard!$F$2:$F$351,"Partial") -> 0 | F19: =COUNTIFS(Scorecard!$B$2:$B$351,$A19,Scorecard!$F$2:$F$351,"Mock") -> 0 | G19: =COUNTIFS(Scorecard!$B$2:$B$351,$A19,Scorecard!$F$2:$F$351,"Absent") -> 12 | H19: =C19+D19 -> 0 | I19: =IFERROR(H19/B19,0) -> 0 | J19: =IFERROR((C19*1+D19*0.85+E19*0.4+F19*0.05)/B19,0) -> 0 | K19: =COUNTIFS(Scorecard!$B$2:$B$351,$A19,Scorecard!$G$2:$G$351,"P0") -> 0 | L19: =COUNTIFS(Scorecard!$B$2:$B$351,$A19,Scorecard!$G$2:$G$351,"P1") -> 0
... A27: T. Nigeria & Africa environment (our own domain) | B27: =COUNTIF(Scorecard!$B$2:$B$351,$A27) -> 24 | C27: =COUNTIFS(Scorecard!$B$2:$B$351,$A27,Scorecard!$F$2:$F$351,"Strong") -> 1 | D27: =COUNTIFS(Scorecard!$B$2:$B$351,$A27,Scorecard!$F$2:$F$351,"Present") -> 0 | E27: =COUNTIFS(Scorecard!$B$2:$B$351,$A27,Scorecard!$F$2:$F$351,"Partial") -> 3 | F27: =COUNTIFS(Scorecard!$B$2:$B$351,$A27,Scorecard!$F$2:$F$351,"Mock") -> 0 | G27: =COUNTIFS(Scorecard!$B$2:$B$351,$A27,Scorecard!$F$2:$F$351,"Absent") -> 20 | H27: =C27+D27 -> 1 | I27: =IFERROR(H27/B27,0) -> 0.041666667 | J27: =IFERROR((C27*1+D27*0.85+E27*0.4+F27*0.05)/B27,0) -> 0.091666667 | K27: =COUNTIFS(Scorecard!$B$2:$B$351,$A27,Scorecard!$G$2:$G$351,"P0") -> 1 | L27: =COUNTIFS(Scorecard!$B$2:$B$351,$A27,Scorecard!$G$2:$G$351,"P1") -> 12
A28: TOTAL | B28: =SUM(B8:B27) -> 350 | C28: =SUM(C8:C27) -> 12 | D28: =SUM(D8:D27) -> 17 | E28: =SUM(E8:E27) -> 54 | F28: =SUM(F8:F27) -> 6 | G28: =SUM(G8:G27) -> 261 | H28: =SUM(H8:H27) -> 29 | I28: =IFERROR(H28/B28,0) -> 0.082857143 | J28: =IFERROR((C28*1+D28*0.85+E28*0.4+F28*0.05)/B28,0) -> 0.13814286 | K28: =SUM(K8:K27) -> 16 | L28: =SUM(L8:L27) -> 82
A31: Coverage by capability class
A32: Class | B32: Meaning | C32: Items | D32: Covered | E32: Coverage %
A33: TS | B33: Table stakes — absence disqualifies you | C33: =COUNTIF(Scorecard!$D$2:$D$351,$A33) -> 130 | D33: =COUNTIFS(Scorecard!$D$2:$D$351,$A33,Scorecard!$F$2:$F$351,"Strong")+COUNTIFS(Scorecard!$D$2:$D$351,$A33,Scorecard!$F$2:$F$351,"Present") -> 25 | E33: =IFERROR(D33/C33,0) -> 0.19230769
A34: D | B34: Differentiator — separates good from average | C34: =COUNTIF(Scorecard!$D$2:$D$351,$A34) -> 163 | D34: =COUNTIFS(Scorecard!$D$2:$D$351,$A34,Scorecard!$F$2:$F$351,"Strong")+COUNTIFS(Scorecard!$D$2:$D$351,$A34,Scorecard!$F$2:$F$351,"Present") -> 4 | E34: =IFERROR(D34/C34,0) -> 0.024539877
A35: LE | B35: Leading edge — few vendors have it in 2026; where you can win | C35: =COUNTIF(Scorecard!$D$2:$D$351,$A35) -> 57 | D35: =COUNTIFS(Scorecard!$D$2:$D$351,$A35,Scorecard!$F$2:$F$351,"Strong")+COUNTIFS(Scorecard!$D$2:$D$351,$A35,Scorecard!$F$2:$F$351,"Present") -> 0 | E35: =IFERROR(D35/C35,0) -> 0
A38: Backlog by priority
A39: Priority | B39: Meaning | C39: Items
A40: P0 | B40: Blocker — unsellable / unsafe until fixed (Phase 0) | C40: =COUNTIF(Scorecard!$G$2:$G$351,$A40) -> 16
A41: P1 | B41: Parity — required to match Corporater (Phases 1-2) | C41: =COUNTIF(Scorecard!$G$2:$G$351,$A41) -> 82
A42: P2 | B42: Moat — where we win (Phases 3-4) | C42: =COUNTIF(Scorecard!$G$2:$G$351,$A42) -> 145
A43: P3 | B43: Beyond — deferrable | C43: =COUNTIF(Scorecard!$G$2:$G$351,$A43) -> 107
A46: How to read this
A47: • Current state assessed from a full read of all 60 migrations, routes/web.php, 20 models, 10 of 14 services and targeted controller method bodies, then independently re-verified against the codebase claim by claim.
A48: • Coverage % counts only Strong + Present. Weighted coverage % scores Strong 1.00, Present 0.85, Partial 0.40, Mock 0.05, Absent 0.00.
A49: • 'Mock' means the feature renders but the numbers are fabricated (mt_rand). Mock is scored below Partial deliberately — it is worse than absent because it is a reputational risk.
A50: • Corporater column reflects their published solution feature list, solution brief and product screenshots. 'Unknown' means not evidenced publicly.
A51: • Domain T is our own addition — the Nigerian and African environment requirements that no global checklist covers, and where the durable moat is.
A52: • Work package references map to 01_EXECUTION_PROMPT_PACK.md.

Sheet Scorecard
A1: # | B1: Domain | C1: Capability | D1: Class | E1: Corporater | F1: Current state | G1: Priority | H1: Work package | I1: Evidence / note
A2: 1 | B2: A. Platform architecture & data model | C2: Metadata-driven object model; new fields without code deployment | D2: TS | E2: Yes | F2: Absent | G2: P1 | H2: WP-03, WP-05 | I2: No metadata layer; all fields are DDL columns
A3: 2 | B3: A. Platform architecture & data model | C3: Configurable object types (not just fields) | D3: D | E3: Yes | F3: Absent | G3: P1 | H3: WP-03, WP-05 | I3: entity_types carries only icon/color/level — no attribute schema
A4: 3 | B4: A. Platform architecture & data model | C4: Configurable, typed relationships between any object types | D4: D | E4: Yes | F4: Absent | G4: P1 | H4: WP-03 | I4: Relationships are hardcoded pivots
A5: 4 | B5: A. Platform architecture & data model | C5: Digital-twin org graph (entity, division, BU, process, system, asset, product, geography) | D5: LE | E5: Yes | F5: Partial | G5: P1 | H5: WP-03 | I5: entities/entity_types is an embryonic version; runs in parallel with business_units — two org models
A6: 5 | B6: A. Platform architecture & data model | C6: Object inheritance/templating so common behaviour is defined once | D6: TS | E6: Yes | F6: Absent | G6: P1 | H6: WP-03
A7: 6 | B7: A. Platform architecture & data model | C7: Period-aware measure model shared by KPIs and KRIs | D7: D | E7: Yes | F7: Absent | G7: P1 | H7: WP-04 | I7: Risk scores are single-valued; no period dimension anywhere
A8: 7 | B8: A. Platform architecture & data model | C8: Point-in-time reconstruction of any object's state ('as at' queries) | D8: D | E8: Yes | F8: Absent | G8: P1 | H8: WP-04 | I8: Reconstructable only indirectly from risk_assessments
A9: 8 | B9: A. Platform architecture & data model | C9: Full versioning and immutable audit trail on every object and field | D9: TS | E9: Yes | F9: Partial | G9: P0 | H9: WP-00, WP-03 | I9: Field-level trail exists but is broken: AuditTrailService writes 'Risk', Risk::auditTrail() queries 'risk'
A10: 9 | B10: A. Platform architecture & data model | C10: Soft delete, archival, configurable retention policies | D10: TS | E10: Yes | F10: Partial | G10: P2 | H10: WP-03 | I10: softDeletes on users/entities only; no retention policy
A11: 10 | B11: A. Platform architecture & data model | C11: Hierarchical roll-up and aggregation derived from the graph | D11: D | E11: Yes | F11: Partial | G11: P1 | H11: WP-03 | I11: Risk::calculateRollUpScore() exists but is risk-specific, not graph-derived
A12: 11 | B12: A. Platform architecture & data model | C12: Multi-entity / multi-org support with data segregation | D12: TS | E12: Yes | F12: Partial | G12: P0 | H12: WP-00 | I12: organization_id on every table but ZERO global scopes; 166 uses of '?? 1' across 22 files; MonteCarloService line 49 reads scenarios with no org filter
A13: 12 | B13: A. Platform architecture & data model | C13: Multi-tenancy with per-tenant configuration divergence | D13: D | E13: Yes | F13: Absent | G13: P1 | H13: WP-05
A14: 13 | B14: A. Platform architecture & data model | C14: Configurable lifecycle states and status models per object type | D14: TS | E14: Yes | F14: Absent | G14: P1 | H14: WP-03 | I14: Status is a hardcoded enum/string per table
A15: 14 | B15: A. Platform architecture & data model | C15: Calculated/derived fields with a formula engine | D15: D | E15: Yes | F15: Absent | G15: P1 | H15: WP-04, WP-05 | I15: Needed for inflation-indexed thresholds
A16: 15 | B16: A. Platform architecture & data model | C16: Configuration as a versioned artefact with dev->test->prod promotion, diff, rollback | D16: D | E16: Unknown | F16: Absent | G16: P2 | H16: WP-05 | I16: Where most configurable platforms fail — real differentiator
A17: 16 | B17: A. Platform architecture & data model | C17: Bulk import/export at object level with validation and error reporting | D17: TS | E17: Yes | F17: Partial | G17: P1 | H17: WP-02, WP-07 | I17: CSV only; xlsx accepted but parsed with fgetcsv; insert-only, no dry-run, no rollback
A18: 17 | B18: A. Platform architecture & data model | C18: Reference/content library with versioned framework packs | D18: D | E18: Yes | F18: Absent | G18: P2 | H18: WP-16 | I18: The moat, productised
A19: 18 | B19: A. Platform architecture & data model | C19: Graph query capability exposed to users and AI agents | D19: LE | E19: No | F19: Absent | G19: P3 | H19: WP-03, WP-07
A20: 19 | B20: A. Platform architecture & data model | C20: Horizontal scalability; documented performance limits | D20: TS | E20: Yes | F20: Absent | G20: P2 | H20: WP-07 | I20: No load testing; Monte Carlo runs synchronously in HTTP
A21: 20 | B21: A. Platform architecture & data model | C21: Sub-second response on registers of 100k+ objects | D21: D | E21: Unknown | F21: Absent | G21: P2 | H21: WP-09
A22: 21 | B22: A. Platform architecture & data model | C22: Localisation of the object model (labels, taxonomies, content per language) | D22: TS | E22: Yes | F22: Absent | G22: P2 | H22: WP-09 | I22: No lang/ directory; 28 __() calls across 142 views
A23: 22 | B23: A. Platform architecture & data model | C23: Currency handling with FX rates by period | D23: D | E23: Unknown | F23: Absent | G23: P2 | H23: WP-04, WP-15 | I23: loss_events.currency is the only currency field and is unused
A24: 23 | B24: A. Platform architecture & data model | C24: Sandbox / what-if branching | D24: LE | E24: No | F24: Absent | G24: P3 | H24: WP-05
A25: 24 | B25: A. Platform architecture & data model | C25: Event-sourced change log enabling replay | D25: LE | E25: No | F25: Partial | G25: P3 | H25: WP-03 | I25: domain_events outbox exists with retry counters
A26: 25 | B26: B. Risk taxonomy, register & appetite | C26: Central risk register with configurable fields | D26: TS | E26: Yes | F26: Present | G26: P1 | H26: WP-05 | I26: Register is strong; fields are not configurable
A27: 26 | B27: B. Risk taxonomy, register & appetite | C27: Configurable multi-level risk taxonomy (3+ levels) | D27: TS | E27: Yes | F27: Present | G27: P1 | H27: WP-10 | I27: risk_categories: self-tree, level, materialized path, cbn_mapping_code, basel_category
A28: 27 | B28: B. Risk taxonomy, register & appetite | C28: Multiple simultaneous taxonomies on one risk | D28: D | E28: Yes | F28: Absent | G28: P1 | H28: WP-10 | I28: One category_id only; risk_taxonomies is a disconnected parallel tree with its own live UI
A29: 28 | B29: B. Risk taxonomy, register & appetite | C29: Risk hierarchy — parent/child, aggregation into themes and principal risks | D29: TS | E29: Yes | F29: Strong | G29: P3 | H29: - | I29: parent_risk_id, risk_level, hierarchy_path, roll_up_weight, calculateRollUpScore()
A30: 29 | B30: B. Risk taxonomy, register & appetite | C30: Risk ownership with named accountable individual and delegation | D30: TS | E30: Yes | F30: Present | G30: P3 | H30: - | I30: risk_owner_id + risk_steward_id; entities have delegate_owner_id
A31: 30 | B31: B. Risk taxonomy, register & appetite | C31: Cause -> risk event -> consequence structure | D31: TS | E31: Yes | F31: Absent | G31: P1 | H31: WP-10 | I31: A risk is a title plus scores; ISO 31000 requires structure
A32: 31 | B32: B. Risk taxonomy, register & appetite | C32: Opportunity modelling alongside threat (ISO 31000 bidirectional) | D32: D | E32: Yes | F32: Absent | G32: P1 | H32: WP-10 | I32: Corporater ships an opportunity heat map; we have no opportunity model at all
A33: 32 | B33: B. Risk taxonomy, register & appetite | C33: Inherent, current/residual and target risk levels | D33: TS | E33: Yes | F33: Partial | G33: P1 | H33: WP-10 | I33: target_rating is a STRING LABEL ONLY — no target L/I/score, so target cannot be plotted
A34: 33 | B34: B. Risk taxonomy, register & appetite | C34: Risk velocity, persistence and proximity attributes | D34: D | E34: Unknown | F34: Partial | G34: P2 | H34: WP-10 | I34: risk_velocity exists; proximity and persistence do not
A35: 34 | B35: B. Risk taxonomy, register & appetite | C35: Emerging risk register distinct from the principal register | D35: TS | E35: Yes | F35: Mock | G35: P1 | H35: WP-02, WP-10 | I35: ai/radar page is mt_rand-generated
A36: 35 | B36: B. Risk taxonomy, register & appetite | C36: Configurable likelihood and consequence scales with definitions per point | D36: TS | E36: Yes | F36: Absent | G36: P1 | H36: WP-05 | I36: 5x5 hardcoded in 3 places; settings written but read by nothing
A37: 36 | B37: B. Risk taxonomy, register & appetite | C37: Multi-dimensional consequence categories | D37: TS | E37: Yes | F37: Present | G37: P2 | H37: WP-05 | I37: financial/operational/reputational/regulatory (+strategic on assessments)
A38: 37 | B38: B. Risk taxonomy, register & appetite | C38: Scales configurable per organizational unit and per risk type | D38: D | E38: Unknown | F38: Absent | G38: P2 | H38: WP-05
A39: 38 | B39: B. Risk taxonomy, register & appetite | C39: Risk appetite statements as first-class objects linked to objectives | D39: TS | E39: Yes | F39: Partial | G39: P1 | H39: WP-10 | I39: Keyed to risk_category_id only; not linked to objectives or nodes
A40: 39 | B40: B. Risk taxonomy, register & appetite | C40: Quantified appetite/tolerance thresholds with automatic breach detection | D40: D | E40: Yes | F40: Partial | G40: P1 | H40: WP-10 | I40: Single tolerance band; RiskAppetiteService reads 5 columns that do not exist - capacity, appetite_type and notes are always fallbacks
A41: 40 | B41: B. Risk taxonomy, register & appetite | C41: Currency-denominated appetite with stated probability of exceedance | D41: LE | E41: No | F41: Absent | G41: P2 | H41: WP-10, WP-18 | I41: White space; unlocked by quantification L5
A42: 41 | B42: B. Risk taxonomy, register & appetite | C42: Risk appetite cascade — group appetite decomposed to BU limits | D42: D | E42: Unknown | F42: Absent | G42: P1 | H42: WP-10 | I42: entities.category_appetites exists but is unused
A43: 42 | B43: B. Risk taxonomy, register & appetite | C43: Risk interdependency / correlation mapping | D43: D | E43: Yes | F43: Partial | G43: P2 | H43: WP-03 | I43: risk_related_risks with relationship_type + correlation_strength
A44: 43 | B44: B. Risk taxonomy, register & appetite | C44: Risk network visualisation showing contagion and concentration | D44: LE | E44: No | F44: Absent | G44: P3 | H44: WP-08
A45: 44 | B45: B. Risk taxonomy, register & appetite | C45: Risk acceptance workflow with sign-off, expiry and re-review | D45: TS | E45: Yes | F45: Absent | G45: P1 | H45: WP-10 | I45: treatment_strategy can be 'accept' with zero governance
A46: 45 | B46: C. Assessment, analysis & methodology | C46: Configurable assessment campaigns with scheduling and reminders | D46: TS | E46: Yes | F46: Present | G46: P2 | H46: - | I46: assessment_campaigns -> campaign_assignments -> campaign_responses
A47: 46 | B47: C. Assessment, analysis & methodology | C47: RCSA with full lifecycle (scope, distribute, respond, challenge, sign-off) | D47: TS | E47: Yes | F47: Partial | G47: P0 | H47: WP-02, WP-11 | I47: RcsaController::storeWorksheet() IS A STUB — submissions silently discarded
A48: 47 | B48: C. Assessment, analysis & methodology | C48: Prior-period pre-population with change highlighting | D48: D | E48: Yes | F48: Absent | G48: P1 | H48: WP-11 | I48: Requires the period model
A49: 48 | B49: C. Assessment, analysis & methodology | C49: Second-line challenge and override workflow | D49: D | E49: Yes | F49: Absent | G49: P1 | H49: WP-11
A50: 49 | B50: C. Assessment, analysis & methodology | C50: Questionnaire builder with conditional logic, scoring and weighting | D50: TS | E50: Yes | F50: Partial | G50: P1 | H50: WP-11 | I50: Schema is AHEAD of market (8 types, conditional_logic, scoring_rules); UI is 915 bytes
A51: 50 | B51: C. Assessment, analysis & methodology | C51: Heat maps with configurable axes, bubble sizing and drill-through | D51: TS | E51: Yes | F51: Partial | G51: P1 | H51: WP-08, WP-11 | I51: Hardcoded 5x5; no cell counts; no drill-through
A52: 51 | B52: C. Assessment, analysis & methodology | C52: Heat map movement / trend visualisation across periods | D52: D | E52: Yes | F52: Absent | G52: P1 | H52: WP-04, WP-08
A53: 52 | B53: C. Assessment, analysis & methodology | C53: Native bow-tie with barriers, escalation factors and barrier effectiveness | D53: D | E53: Unknown | F53: Partial | G53: P2 | H53: WP-11 | I53: Read-only and derived — buildCauses()/buildConsequences() synthesize nodes
A54: 53 | B54: C. Assessment, analysis & methodology | C54: FMEA/FMECA with SxOxD, RPN and AIAG-VDA Action Priority | D54: D | E54: Unknown | F54: Absent | G54: P2 | H54: WP-11
A55: 54 | B55: C. Assessment, analysis & methodology | C55: HAZOP with node/parameter/guide-word structure | D55: D | E55: No | F55: Absent | G55: P3 | H55: WP-11 | I55: Relevant for energy and manufacturing customers
A56: 55 | B56: C. Assessment, analysis & methodology | C56: Root cause analysis (5 Whys, fishbone) | D56: TS | E56: Yes | F56: Strong | G56: P3 | H56: - | I56: loss_event_rca with why_1..why_5, contributory factors, own approval chain
A57: 56 | B57: C. Assessment, analysis & methodology | C57: Fault tree and event tree analysis | D57: D | E57: No | F57: Absent | G57: P3 | H57: WP-11
A58: 57 | B58: C. Assessment, analysis & methodology | C58: Scenario analysis with workshop capture, participants and approval | D58: TS | E58: Yes | F58: Partial | G58: P2 | H58: WP-18 | I58: quantification_scenarios has calibration and approval fields
A59: 58 | B59: C. Assessment, analysis & methodology | C59: Structured expert elicitation with calibration training and bias controls | D59: D | E59: No | F59: Absent | G59: P3 | H59: WP-18
A60: 59 | B60: C. Assessment, analysis & methodology | C60: Control effectiveness feeding residual risk transparently | D60: TS | E60: Yes | F60: Strong | G60: P3 | H60: - | I60: Weighted aggregation via control_weight; but TWO conflicting effectiveness maps exist
A61: 60 | B61: C. Assessment, analysis & methodology | C61: Assessment quality analytics — outlier, boilerplate, peer comparison | D61: D | E61: No | F61: Absent | G61: P2 | H61: WP-11
A62: 61 | B62: C. Assessment, analysis & methodology | C62: AI-assisted RCSA — draft, flag inconsistencies, summarise challenge | D62: LE | E62: No | F62: Absent | G62: P2 | H62: WP-29 | I62: Attacks the biggest quality problem in ERM; almost nobody does it well
A63: 62 | B63: C. Assessment, analysis & methodology | C63: Assessment audit trail — who scored what, when and why | D63: TS | E63: Yes | F63: Present | G63: P3 | H63: - | I63: risk_assessments with rationale, justification, previous_assessment_id chain
A64: 63 | B64: C. Assessment, analysis & methodology | C64: Delphi / multi-round anonymous estimation | D64: D | E64: No | F64: Absent | G64: P3 | H64: WP-11
A65: 64 | B65: C. Assessment, analysis & methodology | C65: Maturity assessments against framework principles | D65: TS | E65: Yes | F65: Absent | G65: P2 | H65: WP-11 | I65: COSO ERM 20 principles, COSO IC 17 principles, ISO 31000 clauses, NIST tiers
A66: 65 | B66: C. Assessment, analysis & methodology | C66: Assurance mapping across the three lines with coverage and gap view | D66: D | E66: Yes | F66: Absent | G66: P2 | H66: WP-24
A67: 66 | B67: C. Assessment, analysis & methodology | C67: Automatic detection of over-assurance and assurance gaps | D67: LE | E67: No | F67: Absent | G67: P3 | H67: WP-24
A68: 67 | B68: D. Risk quantification | C68: Semi-quantitative currency ranges on impact | D68: TS | E68: Yes | F68: Partial | G68: P1 | H68: WP-05 | I68: financial_exposure_ngn exists; scale points carry no currency bands
A69: 68 | B69: D. Risk quantification | C69: Expected loss calculation (frequency x severity) | D69: TS | E69: Yes | F69: Strong | G69: P3 | H69: - | I69: expected_annual_loss_kobo on scenarios
A70: 69 | B70: D. Risk quantification | C70: Monte Carlo engine with configurable iterations and seeds | D70: D | E70: Yes | F70: Present | G70: P1 | H70: WP-18 | I70: 10,000 iterations default; RUNS SYNCHRONOUSLY IN THE HTTP REQUEST; no seed control
A71: 70 | B71: D. Risk quantification | C71: Distribution library (PERT, triangular, lognormal, Poisson, neg-binomial, Weibull, Pareto, GPD, empirical) | D71: D | E71: Unknown | F71: Partial | G71: P2 | H71: WP-18 | I71: Poisson + Lognormal ONLY in code; columns exist for binomial/Pareto/GPD/Weibull
A72: 71 | B72: D. Risk quantification | C72: Distribution fitting to historical loss data with goodness-of-fit | D72: D | E72: No | F72: Absent | G72: P2 | H72: WP-18 | I72: We have the loss data to fit to — real advantage
A73: 72 | B73: D. Risk quantification | C73: FAIR-conformant decomposition (TEF, Vuln, PL, SLEF, SLM, six loss forms) | D73: D | E73: No | F73: Absent | G73: P2 | H73: WP-18 | I73: Corporater has no evidence of FAIR
A74: 73 | B74: D. Risk quantification | C74: FAIR-CAM control analytics | D74: LE | E74: No | F74: Absent | G74: P3 | H74: WP-19
A75: 74 | B75: D. Risk quantification | C75: FAIR-MAM materiality assessment | D75: LE | E75: No | F75: Absent | G75: P3 | H75: WP-19
A76: 75 | B76: D. Risk quantification | C76: Loss exceedance curves as a primary board visual | D76: D | E76: No | F76: Absent | G76: P2 | H76: WP-18 | I76: Should replace the heat map as the board visual
A77: 76 | B77: D. Risk quantification | C77: ALE, VaR and CVaR/Expected Shortfall at configurable confidence levels | D77: D | E77: Partial | F77: Partial | G77: P2 | H77: WP-18 | I77: VaR at 90/95/99/99.9 exists; CVaR does not
A78: 77 | B78: D. Risk quantification | C78: Portfolio aggregation with correlation (rank correlation, copulas) | D78: LE | E78: No | F78: Absent | G78: P2 | H78: WP-19 | I78: correlation_method DEFAULTS TO 'GAUSSIAN_COPULA' but NO COPULA IS IMPLEMENTED
A79: 78 | B79: D. Risk quantification | C79: Sensitivity / tornado analysis | D79: D | E79: Yes | F79: Absent | G79: P2 | H79: WP-18 | I79: Corporater ships EBITDA/FCF/NPV tornado bars
A80: 79 | B80: D. Risk quantification | C80: Control ROI / cost-benefit optimisation | D80: LE | E80: No | F80: Absent | G80: P2 | H80: WP-19 | I80: 'This N400m control reduces 95th-percentile loss by N3.1bn' sells the product
A81: 80 | B81: D. Risk quantification | C81: Scenario-based stress testing and reverse stress testing | D81: D | E81: Yes | F81: Partial | G81: P2 | H81: WP-19 | I81: stress_multiplier_* and stress_config are STORED AND NEVER APPLIED
A82: 81 | B82: D. Risk quantification | C82: LDA — separate frequency/severity, EVT/POT tails, convolution | D82: D | E82: No | F82: Absent | G82: P2 | H82: WP-19 | I82: What a Nigerian bank's ICAAP Pillar 2 actually needs
A83: 82 | B83: D. Risk quantification | C83: Combining internal loss data, external loss data, scenarios and BEICFs | D83: D | E83: Unknown | F83: Partial | G83: P2 | H83: WP-19 | I83: Internal loss data is strong; external and BEICFs absent
A84: 83 | B84: D. Risk quantification | C84: Backtesting quantified estimates against realised losses | D84: LE | E84: No | F84: Absent | G84: P2 | H84: WP-19 | I84: What makes quantification credible to a regulator
A85: 84 | B85: D. Risk quantification | C85: Capital calculation support (Basel SMA, Solvency II SCR) | D85: LE | E85: Partial | F85: Partial | G85: P2 | H85: WP-19 | I85: ICAAP model is correctly structured but Pillar 2A/2B are INPUT fields, not derived
A86: 85 | B86: E. Controls & control monitoring | C86: Central control library with configurable attributes | D86: TS | E86: Yes | F86: Present | G86: P2 | H86: WP-05 | I86: control_type/nature/frequency/automation_level are free-form strings, no vocabulary
A87: 86 | B87: E. Controls & control monitoring | C87: Control classification (preventive/detective, manual/automated, key/non-key) | D87: TS | E87: Yes | F87: Present | G87: P2 | H87: - | I87: is_key_control on the pivot; classification columns unconstrained
A88: 87 | B88: E. Controls & control monitoring | C88: Control-to-risk mapping, many-to-many, with stated mitigation effect | D88: TS | E88: Yes | F88: Strong | G88: P3 | H88: - | I88: risk_control_mapping with control_weight and is_key_control — better than most tools
A89: 88 | B89: E. Controls & control monitoring | C89: Control-to-obligation/framework mapping, multi-framework | D89: TS | E89: Yes | F89: Absent | G89: P1 | H89: WP-20
A90: 89 | B90: E. Controls & control monitoring | C90: Common control model — one control satisfying N requirements, tested once | D90: D | E90: Yes | F90: Absent | G90: P1 | H90: WP-03, WP-20 | I90: Requires typed relationships
A91: 90 | B91: E. Controls & control monitoring | C91: Separate design effectiveness and operating effectiveness | D91: TS | E91: Yes | F91: Partial | G91: P2 | H91: WP-10 | I91: control_tests.test_type includes both but effectiveness is one rating
A92: 91 | B92: E. Controls & control monitoring | C92: Control testing workflow with sampling, evidence, conclusion, reviewer sign-off | D92: TS | E92: Yes | F92: Strong | G92: P3 | H92: - | I92: 4 test types, 4 results, full lifecycle, tester/reviewer separation, evidence upload
A93: 92 | B93: E. Controls & control monitoring | C93: Control deficiency evaluation with escalation to material weakness | D93: TS | E93: Yes | F93: Absent | G93: P2 | H93: WP-10
A94: 93 | B94: E. Controls & control monitoring | C94: Control owner attestation/certification cycles | D94: TS | E94: Yes | F94: Absent | G94: P2 | H94: WP-21
A95: 94 | B95: E. Controls & control monitoring | C95: Control test scripting/automation against source systems | D95: D | E95: No | F95: Absent | G95: P2 | H95: WP-25
A96: 95 | B96: E. Controls & control monitoring | C96: Continuous control monitoring with scheduled automated tests | D96: D | E96: No | F96: Absent | G96: P2 | H96: WP-25 | I96: Corporater gap; Forrester says this is where the market is heading
A97: 96 | B97: E. Controls & control monitoring | C97: Full-population testing rather than sampling | D97: D | E97: No | F97: Absent | G97: P3 | H97: WP-25
A98: 97 | B98: E. Controls & control monitoring | C98: Exception auto-generation into the issue register with owner and SLA | D98: D | E98: Yes | F98: Absent | G98: P2 | H98: WP-25
A99: 98 | B99: E. Controls & control monitoring | C99: Control health score as a continuous time series feeding residual risk | D99: LE | E99: No | F99: Absent | G99: P2 | H99: WP-04, WP-25 | I99: Natural once controls are measures
A100: 99 | B100: E. Controls & control monitoring | C100: Automated evidence capture with immutable provenance and hash | D100: D | E100: No | F100: Absent | G100: P2 | H100: WP-25
...

Sheet Corporater Parity
A1: Corporater ERM — published feature list, scored
A2: The 45+ features Corporater publishes for its Enterprise Risk Management solution. This is the Phase 2 parity target.
A4: # | B4: Corporater feature | C4: Our current state | D4: Priority | E4: Work package | F4: Note
A5: 1 | B5: Access control / permissions | C5: Partial | D5: P0 | E5: WP-00 | F5: Seeded but unenforced — 0 of 203 routes guarded
A6: 2 | B6: Alerts and notifications | C6: Partial | D6: P2 | E6: WP-07 | F6: In-app + DB only; email is a logged placeholder
A7: 3 | B7: Alignment with strategic initiatives, objectives and performance goals | C7: Absent | D7: P2 | E7: WP-27 | F7: No objectives model — the 'P' in Corporater's GPRC
A8: 4 | B8: Audit log | C8: Partial | D8: P0 | E8: WP-00, WP-01 | F8: Exists, mutable, and the read path is broken
A9: 5 | B9: Automated risk reporting | C9: Partial | D9: P0 | E9: WP-12 | F9: On-screen views only; CSV the sole file output; no PDF, no scheduling
A10: 6 | B10: Automated workflows | C10: Partial | D10: P1 | E10: WP-06 | F10: Linear stages; escalation stored and never read
A11: 7 | B11: Business continuity planning | C11: Absent | D11: P2 | E11: WP-23
A12: 8 | B12: Control activities | C12: Present | D12: P3 | E12: - | F12: Control library + testing is genuinely strong
A13: 9 | B13: Customisable branding | C13: Absent | D13: P2 | E13: WP-00 | F13: Brand colours inline in the layout
A14: 10 | B14: Data integration (automated and manual) | C14: Partial | D14: P1 | E14: WP-07 | F14: Manual CSV only; no connectors
A15: 11 | B15: Data visualisation | C15: Partial | D15: P1 | E15: WP-08 | F15: Chart.js from CDN, server-fed, no interactivity
A16: 12 | B16: Digital twin configuration | C16: Partial | D16: P1 | E16: WP-03 | F16: entities/entity_types is embryonic; parallel to business_units
A17: 13 | B17: Document management | C17: Partial | D17: P2 | E17: WP-12 | F17: Read-only aggregator view
A18: 14 | B18: Integrated governance/assurance (AML, Basel & Solvency, InfoSec & Privacy) | C18: Partial | D18: P1 | E18: WP-16, WP-17 | F18: AML and Basel present; Solvency and privacy absent
A19: 15 | B19: Improvement database | C19: Present | D19: P3 | E19: - | F19: Issues + treatments + RCA actions cover this
A20: 16 | B20: Incident management incl. loss/near-loss events | C20: Strong | D20: P3 | E20: - | F20: BEST-IN-CLASS. Exceeds Corporater.
A21: 17 | B21: Integration with underlying risks and information systems | C21: Absent | D21: P1 | E21: WP-07 | F21: No API, no connectors
A22: 18 | B22: Intuitive user interface | C22: Partial | D22: P1 | E22: WP-09 | F22: Server-rendered Blade; no inline edit, no bulk actions, no saved views
A23: 19 | B23: KRI catalog | C23: Present | D23: P2 | E23: WP-04 | F23: Strong definitions; no breach register
... A26: 22 | B26: Opportunity AND consequence heat maps | C26: Partial | D26: P1 | E26: WP-10, WP-08 | F26: Consequence only; NO opportunity model at all
A27: 23 | B27: Policy management for operational risk policies | C27: Absent | D27: P2 | E27: WP-21
A28: 24 | B28: RegTech connectors | C28: Absent | D28: P2 | E28: WP-07
A29: 25 | B29: Risk analysis (scenario, correlation, sensitivity) | C29: Partial | D29: P2 | E29: WP-18, WP-19 | F29: Correlation column exists with no implementation; no sensitivity
A30: 26 | B30: Risk analysis templates | C30: Absent | D30: P2 | E30: WP-16 | F30: Ship as content packs
A31: 27 | B31: Risk appetite | C31: Partial | D31: P1 | E31: WP-10 | F31: Category-level only; service reads 5 non-existent columns
A32: 28 | B32: Risk assessment perspectives (asset, process, external, operational scenario, legal, treasury) | C32: Absent | D32: P1 | E32: WP-03, WP-10 | F32: Assessment contexts with their own ID series and their own ID prefixes (AML-027, BSL2-01, SOD019) — see the screenshots. Treasury/ALM is the one perspective with direct CBN relevance we had not scoped.
A33: 29 | B33: Risk assessments, internal and external, qualitative and quantitative | C33: Present | D33: P2 | E33: WP-11 | F33: Qualitative strong; quantitative exists but is separate
A34: 30 | B34: Risk-bearing capability | C34: Partial | D34: P2 | E34: WP-10, WP-19 | F34: ICAAP capital model exists; not expressed as appetite capacity
A35: 31 | B35: Risk consolidation and aggregation from internal and external sources | C35: Partial | D35: P1 | E35: WP-03, WP-07 | F35: Internal roll-up only
A36: 32 | B36: Risk context | C36: Partial | D36: P1 | E36: WP-10 | F36: ISO 31000 scope/context/criteria not modelled
A37: 33 | B37: Risk Control Self-Assessment (RCSA) | C37: Partial | D37: P0 | E37: WP-02, WP-11 | F37: storeWorksheet() IS A STUB — submissions discarded
A38: 34 | B38: Risk dashboards | C38: Partial | D38: P1 | E38: WP-08 | F38: ONE fixed 48.6 KB dashboard
A39: 35 | B39: Risk data upload via integration and manual input | C39: Partial | D39: P1 | E39: WP-07 | F39: CSV insert-only; xlsx silently mis-parsed
A40: 36 | B40: Risk evaluation | C40: Present | D40: P2 | E40: WP-05 | F40: Hardcoded 5x5 and rating bands
... A42: 38 | B42: Risk heat maps | C42: Partial | D42: P1 | E42: WP-08 | F42: Hardcoded 5x5, no cell counts, no drill-through
A43: 39 | B43: Risk identification (manual and bulk import) based on taxonomy | C43: Present | D43: P2 | E43: -
A44: 40 | B44: Risk mitigation workflows | C44: Present | D44: P2 | E44: WP-06 | F44: Treatment lifecycle is complete; 19 duplicate columns
A45: 41 | B45: Risk modeling | C45: Partial | D45: P2 | E45: WP-18
A46: 42 | B46: Risk monitoring | C46: Present | D46: P2 | E46: WP-04
A47: 43 | B47: Risk probability distribution and simulation incl. Monte Carlo | C47: Present | D47: P1 | E47: WP-18 | F47: Poisson-Lognormal only; runs synchronously in the HTTP request
A48: 44 | B48: Risk radar | C48: Mock | D48: P0 | E48: WP-02 | F48: mt_rand-generated. REMOVE IMMEDIATELY.
A49: 45 | B49: Risk register | C49: Strong | D49: P3 | E49: -
A50: 46 | B50: Risk reporting | C50: Partial | D50: P0 | E50: WP-12 | F50: CSV only
A51: 47 | B51: Risk response | C51: Present | D51: P3 | E51: -
A52: 48 | B52: Risk taxonomies | C52: Present | D52: P1 | E52: WP-10 | F52: One taxonomy in use; a second is orphaned; no multi-taxonomy
A53: 49 | B53: Risk treatment | C53: Strong | D53: P3 | E53: -
A54: 50 | B54: SSO | C54: Absent | D54: P0 | E54: WP-00 | F54: None of any kind
A55: 51 | B55: Strategic risk management | C55: Absent | D55: P2 | E55: WP-27
A56: 52 | B56: Surveys | C56: Partial | D56: P1 | E56: WP-11 | F56: Schema ahead of market; UI is 915 bytes
A57: 53 | B57: Third-party risk management | C57: Absent | D57: P2 | E57: WP-22
A58: 54 | B58: Version control | C58: Absent | D58: P1 | E58: WP-03 | F58: Field-level audit only; no entity versioning or point-in-time
A59: 55 | B59: Link risks to assurance frameworks across the three lines of defense | C59: Absent | D59: P2 | E59: WP-24 | F59: Benefits prose. Assurance mapping with coverage and gap view.
A60: 56 | B60: Correlate risk profile, impact and RISK MATURITY with performance and objectives | C60: Absent | D60: P2 | E60: WP-11, WP-27 | F60: Benefits prose. Risk maturity is a scored, trended assessment, not a label.
A61: 57 | B61: Track treatments and controls across PROJECTS and PORTFOLIOS, not just org units | C61: Absent | D61: P2 | E61: WP-03 | F61: Benefits prose. Project and Portfolio must be first-class risk-bearing node types.
A62: 58 | B62: Four risk responses: avoidance, reduction, SHARING, transfer | C62: Partial | D62: P1 | E62: WP-10 | F62: Benefits prose. We have avoid/mitigate/transfer/accept as a free string. 'Sharing' (joint venture, consortium, co-insurance) is distinct from transfer and unmodelled.
A63: 59 | B63: Automated aggregation of risks UP THE CHAIN | C63: Partial | D63: P1 | E63: WP-03, WP-04 | F63: Benefits prose. Risk::calculateRollUpScore() is risk-specific; graph-derived roll-up is not.
A64: 60 | B64: One shared dynamic register spanning OPERATIONAL to STRATEGIC risk | C64: Partial | D64: P1 | E64: WP-10 | F64: Benefits prose. risk_level enum exists (granular/intermediate/enterprise) but strategic risk carries no distinct attributes.
A65: 61 | B65: KRIs managed against tolerance IN THE CONTEXT OF strategic objectives | C65: Absent | D65: P2 | E65: WP-27 | F65: Benefits prose. Requires an objectives model; KRI-to-objective is distinct from risk-to-objective.
A66: 62 | B66: Standardised reporting process: responsibilities, periodicity, thresholds, formats | C66: Absent | D66: P2 | E66: WP-12 | F66: Benefits prose. A reporting-governance object, not just a report template.
A67: 63 | B67: Evidence of sufficient resources (people and technology) for proactive risk management | C67: Absent | D67: P3 | E67: WP-24 | F67: Benefits prose. Regulators ask this at examination; nobody models it.
A68: 64 | B68: Extendable to compliance, incident, performance and internal audit in ONE system | C68: Absent | D68: P1 | E68: WP-03, WP-05 | F68: The integrated-GRC promise. Only achievable on the object graph — this is the architecture bet stated as a customer benefit.
B70: Total features | C70: =COUNTA(B5:B68) -> 64
B71: Strong or Present | C71: =COUNTIF(C5:C68,"Strong")+COUNTIF(C5:C68,"Present") -> 15
B72: Partial | C72: =COUNTIF(C5:C68,"Partial") -> 28
B73: Absent or Mock | C73: =COUNTIF(C5:C68,"Absent")+COUNTIF(C5:C68,"Mock") -> 21
B74: Weighted parity | C74: =IFERROR((COUNTIF(C5:C68,"Strong")*1+COUNTIF(C5:C68,"Present")*0.85+COUNTIF(C5:C68,"Partial")*0.4+COUNTIF(C5:C68,"Mock")*0.05)/C70,0) -> 0.38203125

Sheet P0-P1 Backlog
A1: P0 and P1 backlog — the critical path
A2: P0 = blocker (unsellable/unsafe until fixed). P1 = required for Corporater parity. Sorted P0 first, then by work package.
A4: Priority | B4: Work package | C4: Domain | D4: Capability | E4: Current state | F4: Evidence / note
A5: P0 | B5: WP-00 | C5: A. Platform architecture & data model | D5: Multi-entity / multi-org support with data segregation | E5: Partial | F5: organization_id on every table but ZERO global scopes; 166 uses of '?? 1' across 22 files; MonteCarloService line 49 reads scenarios with no org filter
A6: P0 | B6: WP-00, WP-03 | C6: A. Platform architecture & data model | D6: Full versioning and immutable audit trail on every object and field | E6: Partial | F6: Field-level trail exists but is broken: AuditTrailService writes 'Risk', Risk::auditTrail() queries 'risk'
A7: P0 | B7: WP-00, WP-05, WP-30 | C7: R. Security, administration & platform governance | D7: RBAC with granular object, field and record-level permissions | E7: Partial | F7: 46 permissions and 9 roles SEEDED; 0 routes use permission middleware; 9 @can across 5 of 142 views
A8: P0 | B8: WP-00, WP-05, WP-30 | C8: R. Security, administration & platform governance | D8: Attribute-based / relationship-derived access control | E8: Absent | F8: Node-scoped authorization
A9: P0 | B9: WP-00, WP-05, WP-30 | C9: R. Security, administration & platform governance | D9: Complete, tamper-evident audit log of all user and system actions | E9: Partial | F9: risk_audit_trail exists but is mutable and the read path is broken
A10: P0 | B10: WP-00, WP-05, WP-30 | C10: R. Security, administration & platform governance | D10: MFA, session management and password/IdP policy enforcement | E10: Partial | F10: EnsureMfaVerified exists, is NOT aliased and is on NO route
A11: P0 | B11: WP-00, WP-05, WP-30 | C11: R. Security, administration & platform governance | D11: Data residency options by region | E11: Absent | F11: CBN localisation deadline: 1 January 2027
A12: P0 | B12: WP-02, WP-11 | C12: C. Assessment, analysis & methodology | D12: RCSA with full lifecycle (scope, distribute, respond, challenge, sign-off) | E12: Partial | F12: RcsaController::storeWorksheet() IS A STUB — submissions silently discarded
A13: P0 | B13: WP-02, WP-28, WP-29 | C13: O. AI & intelligent automation | D13: Predictive risk modelling — likelihood of loss, slippage, control failure | E13: Mock | F13: FABRICATED: hardcoded [0.87,0.73,...] and accuracy 87.3 / auc 0.912 / model_version 2.4.1
A14: P0 | B14: WP-02, WP-28, WP-29 | C14: O. AI & intelligent automation | D14: Full AI traceability — sources, prompt, model, version | E14: Absent | F14: Non-negotiable before any AI ships
A15: P0 | B15: WP-02, WP-28, WP-29 | C15: O. AI & intelligent automation | D15: Human-in-the-loop approval gates on consequential AI actions | E15: Absent
A16: P0 | B16: WP-07 | C16: P. Integration & data | D16: SAML 2.0 / OIDC SSO and SCIM provisioning | E16: Absent | F16: No SSO of any kind; single local password store
A17: P0 | B17: WP-08, WP-12 | C17: N. Reporting, dashboards & analytics | D17: Export to PDF, Word, Excel, PowerPoint | E17: Absent | F17: NO PDF ANYWHERE. Board/regulatory/executive reports render as on-screen views only; generateCustom validates pdf,excel,html,pptx then collapses all four to CSV
A18: P0 | B18: WP-08, WP-12 | C18: N. Reporting, dashboards & analytics | D18: Board pack generation — narrative plus visuals, versioned and approved | E18: Absent
A19: P0 | B19: WP-16, WP-30 | C19: S. Deployment, delivery & commercial | D19: Deployment choice — SaaS, private cloud, on-premise | E19: Partial | F19: Claimed; undermined by CDN asset loading. CBN deadline 1 Jan 2027
A20: P0 | B20: WP-30 | C20: T. Nigeria & Africa environment (our own domain) | D20: Nigeria-resident deployment tier with residency attestation | E20: Absent | F20: CBN PSS/DIR/PUB/CIR/001/004: all payment data in Nigeria by 1 Jan 2027
A21: P1 | B21: - | C21: I. Incidents, events, issues & actions | D21: Incident capture with configurable forms and multi-channel intake | E21: Present | F21: Web only today; USSD/WhatsApp is WP-14
A22: P1 | B22: WP-00, WP-05, WP-30 | C22: R. Security, administration & platform governance | D22: Segregation of duties enforcement within the platform | E22: Partial | F22: Tester/reviewer separation enforced by Gates in control testing only
A23: P1 | B23: WP-00, WP-05, WP-30 | C23: R. Security, administration & platform governance | D23: Encryption in transit and at rest; documented key management | E23: Partial
A24: P1 | B24: WP-02, WP-07 | C24: A. Platform architecture & data model | D24: Bulk import/export at object level with validation and error reporting | E24: Partial | F24: CSV only; xlsx accepted but parsed with fgetcsv; insert-only, no dry-run, no rollback
A25: P1 | B25: WP-02, WP-10 | C25: B. Risk taxonomy, register & appetite | D25: Emerging risk register distinct from the principal register | E25: Mock | F25: ai/radar page is mt_rand-generated
A26: P1 | B26: WP-03 | C26: A. Platform architecture & data model | D26: Configurable, typed relationships between any object types | E26: Absent | F26: Relationships are hardcoded pivots
A27: P1 | B27: WP-03 | C27: A. Platform architecture & data model | D27: Digital-twin org graph (entity, division, BU, process, system, asset, product, geography) | E27: Partial | F27: entities/entity_types is an embryonic version; runs in parallel with business_units — two org models
A28: P1 | B28: WP-03 | C28: A. Platform architecture & data model | D28: Object inheritance/templating so common behaviour is defined once | E28: Absent
A29: P1 | B29: WP-03 | C29: A. Platform architecture & data model | D29: Hierarchical roll-up and aggregation derived from the graph | E29: Partial | F29: Risk::calculateRollUpScore() exists but is risk-specific, not graph-derived
A30: P1 | B30: WP-03 | C30: A. Platform architecture & data model | D30: Configurable lifecycle states and status models per object type | E30: Absent | F30: Status is a hardcoded enum/string per table
A31: P1 | B31: WP-03, WP-05 | C31: A. Platform architecture & data model | D31: Metadata-driven object model; new fields without code deployment | E31: Absent | F31: No metadata layer; all fields are DDL columns
A32: P1 | B32: WP-03, WP-05 | C32: A. Platform architecture & data model | D32: Configurable object types (not just fields) | E32: Absent | F32: entity_types carries only icon/color/level — no attribute schema
A33: P1 | B33: WP-03, WP-05 | C33: A. Platform architecture & data model | D33: Single-platform extension to compliance, incident, performance and internal audit | E33: Absent | F33: The integrated-GRC promise. Only achievable on the object graph — the architecture bet restated as a customer benefit
A34: P1 | B34: WP-03, WP-16 | C34: T. Nigeria & Africa environment (our own domain) | D34: Multi-entity, multi-licence, multi-regulator group modelling | E34: Absent | F34: A Nigerian holdco faces CBN, SEC, NAICOM, PenCom, NDPC concurrently
A35: P1 | B35: WP-03, WP-20 | C35: E. Controls & control monitoring | D35: Common control model — one control satisfying N requirements, tested once | E35: Absent | F35: Requires typed relationships
A36: P1 | B36: WP-04 | C36: A. Platform architecture & data model | D36: Period-aware measure model shared by KPIs and KRIs | E36: Absent | F36: Risk scores are single-valued; no period dimension anywhere
A37: P1 | B37: WP-04 | C37: A. Platform architecture & data model | D37: Point-in-time reconstruction of any object's state ('as at' queries) | E37: Absent | F37: Reconstructable only indirectly from risk_assessments
A38: P1 | B38: WP-04, WP-05 | C38: A. Platform architecture & data model | D38: Calculated/derived fields with a formula engine | E38: Absent | F38: Needed for inflation-indexed thresholds
A39: P1 | B39: WP-04, WP-08 | C39: C. Assessment, analysis & methodology | D39: Heat map movement / trend visualisation across periods | E39: Absent
A40: P1 | B40: WP-04, WP-27 | C40: M. Strategy & performance | D40: Unified KPI/KRI model on one period-aware measure engine | E40: Partial | F40: KRI half exists; KPI half does not. This is Corporater's 'P' in GPRC and their stated differentiator.
A41: P1 | B41: WP-05 | C41: A. Platform architecture & data model | D41: Multi-tenancy with per-tenant configuration divergence | E41: Absent
A42: P1 | B42: WP-05 | C42: B. Risk taxonomy, register & appetite | D42: Central risk register with configurable fields | E42: Present | F42: Register is strong; fields are not configurable
A43: P1 | B43: WP-05 | C43: B. Risk taxonomy, register & appetite | D43: Configurable likelihood and consequence scales with definitions per point | E43: Absent | F43: 5x5 hardcoded in 3 places; settings written but read by nothing
A44: P1 | B44: WP-05 | C44: D. Risk quantification | D44: Semi-quantitative currency ranges on impact | E44: Partial | F44: financial_exposure_ngn exists; scale points carry no currency bands
A45: P1 | B45: WP-05, WP-08, WP-09, WP-13 | C45: Q. UX, configurability & accessibility | D45: No-code field and form builder with conditional visibility | E45: Absent
A46: P1 | B46: WP-05, WP-08, WP-09, WP-13 | C46: Q. UX, configurability & accessibility | D46: No-code object type builder | E46: Absent
A47: P1 | B47: WP-05, WP-08, WP-09, WP-13 | C47: Q. UX, configurability & accessibility | D47: No-code relationship builder | E47: Absent
A48: P1 | B48: WP-05, WP-08, WP-09, WP-13 | C48: Q. UX, configurability & accessibility | D48: BPMN 2.0 visual workflow designer with parallel, timers, escalation, SLA | E48: Partial | F48: Linear JSON stages only; escalation_rules stored and never read; delegate/escalate/return logged but change nothing
A49: P1 | B49: WP-05, WP-08, WP-09, WP-13 | C49: Q. UX, configurability & accessibility | D49: No-code dashboard and widget builder | E49: Absent
A50: P1 | B50: WP-05, WP-08, WP-09, WP-13 | C50: Q. UX, configurability & accessibility | D50: 'My Responsibilities' personal work queue from ownership relationships | E50: Absent | F50: THE highest-leverage adoption feature
A51: P1 | B51: WP-05, WP-08, WP-09, WP-13 | C51: Q. UX, configurability & accessibility | D51: Org-node landing pages ('Business HQ') — navigate by entity, not module | E51: Absent | F51: Inverts the navigation model; how executives actually think
A52: P1 | B52: WP-05, WP-08, WP-09, WP-13 | C52: Q. UX, configurability & accessibility | D52: Lightweight first-line experience optimised for 60-second interactions | E52: Absent | F52: Archer Engage exists because the main UI is too heavy for occasional users
A53: P1 | B53: WP-05, WP-08, WP-09, WP-13 | C53: Q. UX, configurability & accessibility | D53: Native mobile / offline capture with photo and GPS | E53: Absent | F53: In Nigeria this is also a connectivity and power requirement
A54: P1 | B54: WP-05, WP-08, WP-09, WP-13 | C54: Q. UX, configurability & accessibility | D54: Global search across all object types with permission filtering | E54: Absent
A55: P1 | B55: WP-07 | C55: P. Integration & data | D55: REST API covering the full object model | E55: Absent | F55: routes/api.php DOES NOT EXIST
A56: P1 | B56: WP-07 | C56: P. Integration & data | D56: OpenAPI specification and interactive API docs | E56: Absent
A57: P1 | B57: WP-07 | C57: P. Integration & data | D57: Webhooks / outbound event streaming | E57: Absent | F57: domain_events outbox exists but has no outbound transport
A58: P1 | B58: WP-07 | C58: P. Integration & data | D58: OAuth 2.0 / OIDC for API auth | E58: Absent | F58: No Sanctum, no Passport
A59: P1 | B59: WP-07 | C59: P. Integration & data | D59: Bulk import/export with validation, staging and rollback | E59: Partial | F59: CSV insert-only; no dry-run, no rollback; xlsx silently mis-parsed
A60: P1 | B60: WP-08 | C60: E. Controls & control monitoring | D60: Control effectiveness dashboards by entity, process and framework | E60: Partial | F60: testing-dashboard.blade.php is 4.7 KB
A61: P1 | B61: WP-08, WP-11 | C61: C. Assessment, analysis & methodology | D61: Heat maps with configurable axes, bubble sizing and drill-through | E61: Partial | F61: Hardcoded 5x5; no cell counts; no drill-through
A62: P1 | B62: WP-08, WP-12 | C62: N. Reporting, dashboards & analytics | D62: Role-based dashboards with drill-down to source object | E62: Absent | F62: One 48.6 KB fixed dashboard; no roles, no drill-down
A63: P1 | B63: WP-08, WP-12 | C63: N. Reporting, dashboards & analytics | D63: Context-bound widgets — one definition rendering per org node | E63: Absent | F63: The single biggest demo differentiator
A64: P1 | B64: WP-08, WP-12 | C64: N. Reporting, dashboards & analytics | D64: Widget library — heat map, bubble, trend, gauge, table, treemap, network, Gantt | E64: Partial | F64: Chart.js from CDN, server-fed, ~8 chart types, no interactivity
A65: P1 | B65: WP-08, WP-12 | C65: N. Reporting, dashboards & analytics | D65: User-configurable personal dashboards | E65: Absent
A66: P1 | B66: WP-08, WP-12 | C66: N. Reporting, dashboards & analytics | D66: Report builder with templates, filters and parameters | E66: Partial | F66: reports/custom exists; validates 4 formats and emits CSV for all of them
A67: P1 | B67: WP-08, WP-12 | C67: N. Reporting, dashboards & analytics | D67: Period-over-period comparison and movement analysis | E67: Absent | F67: Requires the period model
A68: P1 | B68: WP-10 | C68: B. Risk taxonomy, register & appetite | D68: Configurable multi-level risk taxonomy (3+ levels) | E68: Present | F68: risk_categories: self-tree, level, materialized path, cbn_mapping_code, basel_category
A69: P1 | B69: WP-10 | C69: B. Risk taxonomy, register & appetite | D69: Multiple simultaneous taxonomies on one risk | E69: Absent | F69: One category_id only; risk_taxonomies is a disconnected parallel tree with its own live UI
A70: P1 | B70: WP-10 | C70: B. Risk taxonomy, register & appetite | D70: Cause -> risk event -> consequence structure | E70: Absent | F70: A risk is a title plus scores; ISO 31000 requires structure
A71: P1 | B71: WP-10 | C71: B. Risk taxonomy, register & appetite | D71: Opportunity modelling alongside threat (ISO 31000 bidirectional) | E71: Absent | F71: Corporater ships an opportunity heat map; we have no opportunity model at all
A72: P1 | B72: WP-10 | C72: B. Risk taxonomy, register & appetite | D72: Inherent, current/residual and target risk levels | E72: Partial | F72: target_rating is a STRING LABEL ONLY — no target L/I/score, so target cannot be plotted
A73: P1 | B73: WP-10 | C73: B. Risk taxonomy, register & appetite | D73: Risk appetite statements as first-class objects linked to objectives | E73: Partial | F73: Keyed to risk_category_id only; not linked to objectives or nodes
A74: P1 | B74: WP-10 | C74: B. Risk taxonomy, register & appetite | D74: Quantified appetite/tolerance thresholds with automatic breach detection | E74: Partial | F74: Single tolerance band; RiskAppetiteService reads 5 columns that do not exist - capacity, appetite_type and notes are always fallbacks
A75: P1 | B75: WP-10 | C75: B. Risk taxonomy, register & appetite | D75: Risk appetite cascade — group appetite decomposed to BU limits | E75: Absent | F75: entities.category_appetites exists but is unused
A76: P1 | B76: WP-10 | C76: B. Risk taxonomy, register & appetite | D76: Risk acceptance workflow with sign-off, expiry and re-review | E76: Absent | F76: treatment_strategy can be 'accept' with zero governance
A77: P1 | B77: WP-10 | C77: B. Risk taxonomy, register & appetite | D77: Four-strategy risk response including risk SHARING as distinct from transfer | E77: Partial | F77: treatment_plans.strategy is a free string (avoid/mitigate/transfer/accept). Sharing — JV, consortium, co-insurance, syndication — is a distinct response with its own counterparty and residual profile
... A79: P1 | B79: WP-11 | C79: C. Assessment, analysis & methodology | D79: Prior-period pre-population with change highlighting | E79: Absent | F79: Requires the period model
A80: P1 | B80: WP-11 | C80: C. Assessment, analysis & methodology | D80: Second-line challenge and override workflow | E80: Absent
A81: P1 | B81: WP-11 | C81: C. Assessment, analysis & methodology | D81: Questionnaire builder with conditional logic, scoring and weighting | E81: Partial | F81: Schema is AHEAD of market (8 types, conditional_logic, scoring_rules); UI is 915 bytes
A82: P1 | B82: WP-11, WP-16 | C82: C. Assessment, analysis & methodology | D82: Treasury / ALM assessment perspective (IRRBB, liquidity, FX, counterparty) | E82: Absent | F82: Named explicitly by Corporater. Direct CBN relevance — IRRBB is a Pillar 2 risk type in the ICAAP model we already have
A83: P1 | B83: WP-12, WP-16 | C83: F. Compliance, obligations & regulatory change | D83: Regulatory reporting pack generation (ICAAP, ORSA, self-assessment) | E83: Partial | F83: ICAAP model exists; output is CSV
A84: P1 | B84: WP-13 | C84: T. Nigeria & Africa environment (our own domain) | D84: Offline-first architecture with deterministic conflict resolution | E84: Absent | F84: ~190m mobile subs vs ~110m broadband; branch staff on metered 2G/3G they pay for
A85: P1 | B85: WP-13 | C85: T. Nigeria & Africa environment (our own domain) | D85: PWA, installable, low-bandwidth (<200 KB initial, <3 s FMP at 2G) | E85: Absent
A86: P1 | B86: WP-13 | C86: T. Nigeria & Africa environment (our own domain) | D86: Autosave and power-cut resilience on every form | E86: Absent | F86: Grid collapsed again in 2026; ~70% of businesses on generators
A87: P1 | B87: WP-15 | C87: T. Nigeria & Africa environment (our own domain) | D87: Naira-native multi-currency with CBN official / NAFEM / parallel rate types | E87: Absent | F87: loss_events.currency is the only currency field and is unused
A88: P1 | B88: WP-15 | C88: T. Nigeria & Africa environment (our own domain) | D88: Inflation-indexed threshold formulas with re-baselining approval | E88: Absent | F88: Fixes the 'everything is High' drift; inflation 15.91% June 2026
A89: P1 | B89: WP-16 | C89: T. Nigeria & Africa environment (our own domain) | D89: CBN prudential obligation library and returns calendar | E89: Partial | F89: RegulatoryThresholdService encodes real citations and clocks — a genuine head start
A90: P1 | B90: WP-16 | C90: T. Nigeria & Africa environment (our own domain) | D90: ICAAP as a first-class object with April deadline workflow | E90: Partial | F90: icaap_assessments is correctly structured; Pillar 2 values are inputs, not derived
A91: P1 | B91: WP-16 | C91: T. Nigeria & Africa environment (our own domain) | D91: CBN cyber returns calendar (24h BSD, 28 Feb CSAT, monthly CTI by the 5th) | E91: Absent
A92: P1 | B92: WP-16 | C92: T. Nigeria & Africa environment (our own domain) | D92: Nigerian risk taxonomy (insecurity, diesel, FX repatriation, agents, cash-in-transit) | E92: Absent | F92: No global ERM taxonomy models these
A93: P1 | B93: WP-16, WP-30 | C93: S. Deployment, delivery & commercial | D93: SaaS multi-tenant delivery | E93: Partial | F93: Tenancy exists in the schema but is not enforced
A94: P1 | B94: WP-16, WP-30 | C94: S. Deployment, delivery & commercial | D94: Accelerator / starter content packs for rapid time-to-value | E94: Absent | F94: THE number-one reason global tools get bought and abandoned here
A95: P1 | B95: WP-17 | C95: T. Nigeria & Africa environment (our own domain) | D95: NDPA 2023 + GAID 2025 module (72h breach, DPIA, CAR, DPO CPD, ROPA) | E95: Partial | F95: issues.ndpa_reportable exists; no module. SGF Circular 59805 = hundreds of MDA buyers
A96: P1 | B96: WP-18 | C96: D. Risk quantification | D96: Monte Carlo engine with configurable iterations and seeds | E96: Present | F96: 10,000 iterations default; RUNS SYNCHRONOUSLY IN THE HTTP REQUEST; no seed control
A97: P1 | B97: WP-20 | C97: E. Controls & control monitoring | D97: Control-to-obligation/framework mapping, multi-framework | E97: Absent
A98: P1 | B98: WP-20 | C98: F. Compliance, obligations & regulatory change | D98: Regulatory obligation register at requirement/clause level | E98: Absent | F98: regulatory_circulars tracks documents, not obligations
A99: P1 | B99: WP-20 | C99: F. Compliance, obligations & regulatory change | D99: Obligation -> policy -> control -> risk -> process linkage chain | E99: Absent | F99: The compliance spine
A100: P1 | B100: WP-20 | C100: F. Compliance, obligations & regulatory change | D100: Multi-framework support with cross-mapping | E100: Partial | F100: regulatory_risk_mapping exists; no framework model
A101: P1 | B101: WP-20 | C101: F. Compliance, obligations & regulatory change | D101: Regulatory interaction/examination management | E101: Partial | F101: issues.cbn_examination_finding exists; no examination object
A102: P1 | B102: WP-30 | C102: T. Nigeria & Africa environment (our own domain) | D102: Naira pricing, locally invoiced, flat or entity-tiered (never per-seat) | E102: Absent | F102: Per-seat pricing structurally kills front-line capture

Sheet Legend
A1: Legend and method
A4: CURRENT STATE | B4: Meaning | C4: Weight in the weighted-coverage score
A5: Strong | B5: Best-in-class; exceeds or matches the benchmark | C5: 1.00
A6: Present | B6: Implemented and usable; may need uplift | C6: 0.85
A7: Partial | B7: Partially implemented, or schema exists without UI/behaviour | C7: 0.40
A8: Mock | B8: Renders but the numbers are fabricated (mt_rand) — worse than absent | C8: 0.05
A9: Absent | B9: Not implemented | C9: 0.00
A11: CLASS | B11: Meaning
A12: TS | B12: Table stakes — absence disqualifies you from an evaluation
A13: D | B13: Differentiator — separates good products from average ones
A14: LE | B14: Leading edge — few vendors have it in 2026; where you can win
A16: PRIORITY | B16: Meaning | C16: Phase
A17: P0 | B17: Blocker — unsellable or unsafe until fixed | C17: Phase 0 (weeks 1-4)
A18: P1 | B18: Parity — required to match Corporater | C18: Phases 1-2 (weeks 5-24)
A19: P2 | B19: Moat — where we win against every competitor | C19: Phases 3-4 (weeks 21-44)
A20: P3 | B20: Beyond — valuable but deferrable | C20: Later
A22: CORPORATER | B22: Meaning
A23: Yes | B23: Published in their solution feature list, brief or screenshots
A24: Partial | B24: Claimed but not evidenced in depth
A25: No | B25: Not offered
A26: Unknown | B26: Not evidenced publicly either way
A28: SOURCES
A29: Codebase | B29: Full read of all 60 migrations, routes/web.php, composer.json, bootstrap, config, 4 middleware, 20 models, 10 of 14 services, seeders, and targeted controller method bodies, plus an independent adversarial verification pass over 42 specific factual claims.
A30: Corporater | B30: corporater.com/solution/enterprise-risk-management-software, the 4-page Enterprise Risk Management Solution Brief, and 12 product screenshots.
A31: Benchmark | B31: Riskonnect, MetricStream, Archer, IBM OpenPages, ServiceNow IRM, LogicManager, SAI360, Diligent, Resolver, Protecht, Camms, Origami, Workiva; Verdantix Green Quadrant GRC 2025, Gartner MQ GRC Tools 2025.
A32: Standards | B32: ISO 31000:2018, COSO ERM 2017, COSO IC 2013, ISO 27001:2022, ISO 27005, ISO 22301, ISO 37301, ISO 42001, NIST CSF 2.0, Basel II/III operational risk, Solvency II, IFRS S1/S2, TCFD, DORA, FAIR, IIA Three Lines 2020.
A33: Nigeria / Africa | B33: CBN circulars and guidelines, NDIC, SEC Nigeria, NAICOM, PenCom, NCC, NUPRC/NMDPRA, NERC, FRC, NDPA 2023 + GAID 2025, NITDA National Cloud Policy 2025, Bank of Ghana, CBK Kenya, King V South Africa, POPIA.
